homology/__init__.py
homology/dim0.cpython-38-x86_64-linux-gnu.so
homology/dim1.cpython-38-x86_64-linux-gnu.so
multidim/__init__.py
multidim/covertree.py
multidim/models.py
multidim/multidim_fast_algorithms.cpython-38-x86_64-linux-gnu.so
multidim/test_barycenters.py
multidim/test_cder.py
multidim/test_cder_cv.py
multidim/test_connected_pc.py
multidim/test_covertree.py
multidim/test_gaussian.py
multidim/test_lower_star_for_image.py
multidim/test_multilabel.py
multidim/test_rca1.py
multidim/test_sever_cx.py
multidim/test_sever_pc.py
timeseries/__init__.py
timeseries/curve_geometry.cpython-38-x86_64-linux-gnu.so
timeseries/test_connected.py
timeseries/test_mollifier.py
timeseries/test_spacecurve.py
timeseries/timeseries_fast_algorithms.cpython-38-x86_64-linux-gnu.so
gda_public-1.0.post3.dist-info/COPYING
gda_public-1.0.post3.dist-info/LICENSE
gda_public-1.0.post3.dist-info/METADATA
gda_public-1.0.post3.dist-info/WHEEL
gda_public-1.0.post3.dist-info/top_level.txt
gda_public-1.0.post3.dist-info/RECORD
